arbiter.v
module arbiter(
	req_0,
	req_1,
	req_2,
	req_3,
	gnt_0,
	gnt_1,
	gnt_2,
	gnt_3,
	clk,
	rst
);

input req_0,req_1,req_2,req_3;
input clk;
input rst;
output reg gnt_0,gnt_1,gnt_2,gnt_3;


parameter IDLE = 3'b000;
parameter GNT_0 = 3'b001;
parameter GNT_1 = 3'b010;
parameter GNT_2 = 3'b011;
parameter GNT_3 = 3'b100;

reg [2:0] present_state;
reg [2:0] next_state;

always @(posedge clk) begin
	if(rst) begin
		gnt_0 <= 0;
		gnt_1 <= 0;
		gnt_2 <= 0;
		gnt_3 <= 0;
		present_state <= IDLE;
	end
	else begin
		present_state <= next_state;

		case(present_state) 

			IDLE:	begin
						gnt_0 <= 1'b0;
						gnt_1 <= 1'b0;
						gnt_2 <= 1'b0;
						gnt_3 <= 1'b0;
					end

			GNT_0:	begin
						gnt_0 <= 1'b1;
					end	

			GNT_1:	begin
						gnt_1 <= 1'b1;
					end	

			GNT_2:	begin
						gnt_2 <= 1'b1;
					end	

			GNT_3:	begin
						gnt_3 <= 1'b1;
					end	

			default:	begin
							present_state <= IDLE;
						end
		endcase
	end
end

always @(present_state,req_0,req_1,req_2,req_3) begin
	next_state = 0;

	case(present_state)

		IDLE:	if(req_0 == 3'b1) begin
					next_state = GNT_0;
				end
				else if(req_1 == 3'b1) begin
					next_state = GNT_1;
				end
				else if(req_2 == 3'b1) begin
					next_state = GNT_2;
				end
				else if(req_3 == 3'b1) begin
					next_state = GNT_3;
				end
				else begin
					 next_state = IDLE;
				end

		GNT_0:	if(req_0 == 3'b0) begin
					next_state = IDLE;
				end
				else begin
					next_state = GNT_0;
				end

		GNT_1:	if(req_1 == 3'b0) begin
					next_state = IDLE;
				end
				else begin
					next_state = GNT_1;
				end

		GNT_2:	if(req_2 == 3'b0) begin
					next_state = IDLE;
				end
				else begin
					next_state = GNT_2;
				end

		GNT_3:	if(req_3 == 3'b0) begin
					next_state = IDLE;
				end
				else begin
					next_state = GNT_3;
				end

		default:	next_state = IDLE;

	endcase
end

endmodule

arbiter_tb.v
`include "arbiter.v"

module arbiter_tb;

reg clk,rst;
reg req_0,req_1,req_2,req_3;
wire gnt_0,gnt_1,gnt_2,gnt_3;

arbiter uut(
	.req_0(req_0),
	.req_1(req_1),
	.req_2(req_2),
	.req_3(req_3),
	.gnt_0(gnt_0),
	.gnt_1(gnt_1),
	.gnt_2(gnt_2),
	.gnt_3(gnt_3),
	.clk(clk),
	.rst(rst)
	);

initial begin
	forever #5 clk = ~clk;
end

initial begin
	req_0 = 0;
	req_1 = 0;
	req_2 = 0;
	req_3 = 0;
	clk = 0;
	rst = 0;

	#5 rst = 1;

	#2 rst = 0;
end

initial begin
		
	#10 req_0 = 1;

	#10 req_0 = 0;
	#20 req_1 = 1;

	#10 req_1 = 0;
	#20 req_2 = 1;

	#10 req_2 = 0;
	#20 req_3 = 1;

	#200 $finish;

end

initial begin
	$monitor("time = %t,clk = %b,req_0 = %b,req_1 = %b,req_2 = %b,req_3 = %b,gnt_0 = %b,gnt_1 = %b,gnt_2 = %b,gnt_3 = %b",
			$time,clk,req_0,req_1,req_2,req_3,gnt_0,gnt_1,gnt_2,gnt_3);

	$dumpfile("arbiter.vcd");
	$dumpvars(0,arbiter_tb);
end

endmodule

arbiter.vcd
$date
	Mon Jun 18 08:02:44 2018
$end
$version
	Icarus Verilog
$end
$timescale
	1s
$end
$scope module arbiter_tb $end
$var wire 1 ! gnt_0 $end
$var wire 1 " gnt_1 $end
$var wire 1 # gnt_2 $end
$var wire 1 $ gnt_3 $end
$var reg 1 % clk $end
$var reg 1 & req_0 $end
$var reg 1 ' req_1 $end
$var reg 1 ( req_2 $end
$var reg 1 ) req_3 $end
$var reg 1 * rst $end
$scope module uut $end
$var wire 1 + clk $end
$var wire 1 , req_0 $end
$var wire 1 - req_1 $end
$var wire 1 . req_2 $end
$var wire 1 / req_3 $end
$var wire 1 0 rst $end
$var reg 1 1 gnt_0 $end
$var reg 1 2 gnt_1 $end
$var reg 1 3 gnt_2 $end
$var reg 1 4 gnt_3 $end
$var reg 3 5 next_state [2:0] $end
$var reg 3 6 present_state [2:0] $end
$upscope $end
$upscope $end
$enddefinitions $end
#0
$dumpvars
bx 6
b0 5
x4
x3
x2
x1
00
0/
0.
0-
0,
0+
0*
0)
0(
0'
0&
0%
x$
x#
x"
x!
$end
#5
b0 6
04
0$
03
0#
02
0"
01
0!
1*
10
1%
1+
#7
0*
00
#10
b1 5
0%
0+
1&
1,
#15
b1 5
b1 6
1%
1+
#20
b0 5
0%
0+
0&
0,
#25
11
1!
b0 6
1%
1+
#30
0%
0+
#35
01
0!
1%
1+
#40
b10 5
0%
0+
1'
1-
#45
b10 5
b10 6
1%
1+
#50
b0 5
0%
0+
0'
0-
#55
12
1"
b0 6
1%
1+
#60
0%
0+
#65
02
0"
1%
1+
#70
b11 5
0%
0+
1(
1.
#75
b11 5
b11 6
1%
1+
#80
b0 5
0%
0+
0(
0.
#85
13
1#
b0 6
1%
1+
#90
0%
0+
#95
03
0#
1%
1+
#100
b100 5
0%
0+
1)
1/
#105
b100 5
b100 6
1%
1+
#110
0%
0+
#115
14
1$
1%
1+
